BreathFinder/BreathFinder.py
BreathFinder/__init__.py
BreathFinder-0.2.2.dist-info/LICENSE
BreathFinder-0.2.2.dist-info/METADATA
BreathFinder-0.2.2.dist-info/WHEEL
BreathFinder-0.2.2.dist-info/top_level.txt
BreathFinder-0.2.2.dist-info/RECORD
