Metadata-Version: 2.1
Name: BreathFinder
Version: 0.2.2
Summary: Algorithm designed to find locations of
Home-page: https://github.com/benedikthth/BreathFinder
Author: Benedikt Holm Thordarson
Author-email: b@spock.is
License: MIT
Platform: UNKNOWN
Requires-Dist: numpy
Requires-Dist: scipy
Requires-Dist: sklearn
